setup.cfg
setup.py
krzbackup/__init__.py
krzbackup/elastic.py
krzbackup/file.py
krzbackup/mariadb.py
krzbackup/mongo.py
krzbackup/retention.py
krzbackup/service.py
krzbackup.egg-info/PKG-INFO
krzbackup.egg-info/SOURCES.txt
krzbackup.egg-info/dependency_links.txt
krzbackup.egg-info/requires.txt
krzbackup.egg-info/top_level.txt