Metadata-Version: 1.0
Name: krzbackup
Version: 0.1.11
Summary: A custom backuplibrary to coordinate multiple services
Home-page: http://git.mw-krz-swd.de/Meldewesen/Backup
Author: Kevin Honka
Author-email: k.honka@krz-swd.de
License: GPLv3
Keywords: Backup,Mysql,MariaDB,Elasticsearch,MongoDB
Platform: UNKNOWN
